cheetah_orm/__init__.py
cheetah_orm/constants.py
cheetah_orm/error.py
cheetah_orm/fields.py
cheetah_orm/indexes.py
cheetah_orm/mappers.py
cheetah_orm/migrators.py
cheetah_orm/model.py
cheetah_orm-2.0.0b7.dist-info/LICENSE
cheetah_orm-2.0.0b7.dist-info/METADATA
cheetah_orm-2.0.0b7.dist-info/WHEEL
cheetah_orm-2.0.0b7.dist-info/top_level.txt
cheetah_orm-2.0.0b7.dist-info/RECORD
