Metadata-Version: 2.1
Name: cheetah-orm
Version: 2.0.0b7
Summary: A lightweight and high-performance object-relational mapper for Python.
Author-email: Cybermals <cybermals@googlegroups.com>
License: MIT
Keywords: object-relational mapper
Classifier: Development Status :: 4 - Beta
Classifier: License :: OSI Approved :: MIT License
Classifier: Operating System :: OS Independent
Classifier: Programming Language :: Python :: 3
Classifier: Topic :: Database
Requires-Python: >=3
License-File: LICENSE
Requires-Dist: passlib
Provides-Extra: mariadb
Requires-Dist: pymysql ; extra == 'mariadb'
Provides-Extra: mysql
Requires-Dist: pymysql ; extra == 'mysql'
Provides-Extra: postgresql
Requires-Dist: psycopg ; extra == 'postgresql'
